{"stats":{"minecraft:picked_up":{"minecraft:oak_log":1,"minecraft:melon_slice":6,"minecraft:chest":1,"minecraft:dirt":6,"minecraft:birch_log":1},"minecraft:custom":{"minecraft:open_chest":2,"minecraft:time_since_rest":3685,"minecraft:sprint_one_cm":2302,"minecraft:deaths":1,"minecraft:crouch_one_cm":4779,"minecraft:play_time":4021,"minecraft:damage_taken":240,"minecraft:walk_one_cm":4538,"minecraft:sneak_time":1963,"minecraft:mob_kills":2,"minecraft:jump":6,"minecraft:damage_dealt":141,"minecraft:leave_game":2,"minecraft:time_since_death":3658,"minecraft:total_world_time":4021,"minecraft:fall_one_cm":209,"minecraft:interact_with_crafting_table":2,"minecraft:fly_one_cm":834},"minecraft:killed":{"minecraft:sheep":1},"minecraft:used":{"minecraft:wooden_sword":6,"minecraft:dirt":4,"minecraft:wooden_shovel":25},"minecraft:mined":{"minecraft:podzol":3,"minecraft:chest":1,"minecraft:grass_block":18,"minecraft:oak_log":4,"minecraft:melon":1,"minecraft:birch_log":2,"minecraft:clay":2},"minecraft:crafted":{"minecraft:wooden_sword":1,"minecraft:oak_planks":8,"minecraft:stick":4,"minecraft:wooden_pickaxe":1}},"DataVersion":4082}